beatz/__init__.py
beatz/execute.py
beatz/main.py
beatz/player.py
beatz/version.py
beatz/youtube_helper.py
beatz-0.1.0.dist-info/LICENSE
beatz-0.1.0.dist-info/METADATA
beatz-0.1.0.dist-info/WHEEL
beatz-0.1.0.dist-info/entry_points.txt
beatz-0.1.0.dist-info/top_level.txt
beatz-0.1.0.dist-info/RECORD
