Metadata-Version: 2.1
Name: beatz
Version: 0.1.0
Summary: Download & stream music on your terminal
Home-page: https://github.com/yadneshk/beatz
Author: yadneshk
Author-email: yadnesh45@gmail.com
License: UNKNOWN
Platform: UNKNOWN
Requires-Dist: validators (==0.15.0)
Requires-Dist: youtube-dl (==2020.6.16.1)
